tlo/__init__.py
tlo/common.py
tlo/context.py
tlo/errors.py
tlo/executor/__init__.py
tlo/executor/executor.py
tlo/locking/__init__.py
tlo/locking/locker.py
tlo/logging.py
tlo/orchestrator/__init__.py
tlo/orchestrator/orchestrator.py
tlo/py.typed
tlo/queue/__init__.py
tlo/queue/queue.py
tlo/queue/queued_item.py
tlo/scheduler/__init__.py
tlo/scheduler/scheduler.py
tlo/settings.py
tlo/task_registry/__init__.py
tlo/task_registry/registry.py
tlo/task_registry/task_def.py
tlo/task_state_store/__init__.py
tlo/task_state_store/common.py
tlo/task_state_store/state_store.py
tlo/tlo_types.py
tlo/utils/__init__.py
tlo/utils/coercers.py
tlo_runner-0.1.0.dist-info/WHEEL
tlo_runner-0.1.0.dist-info/METADATA
tlo_runner-0.1.0.dist-info/RECORD
