Metadata-Version: 2.3
Name: tlo-runner
Version: 0.1.0
Summary: Lightweight async background task runner and orcestrator
Keywords: background task runner,task runner,background tasks,async,job queue
Author: TwilightSparkle42
Author-email: TwilightSparkle42 <jaden.corr42@gmail.com>
License: BSD 3-Clause License
Classifier: Development Status :: 3 - Alpha
Classifier: Intended Audience :: Developers
Classifier: License :: OSI Approved :: BSD License
Classifier: Operating System :: OS Independent
Classifier: Programming Language :: Python :: 3
Classifier: Programming Language :: Python :: 3.12
Classifier: Programming Language :: Python :: 3.13
Classifier: Programming Language :: Python :: 3.14
Classifier: Topic :: Utilities
Requires-Dist: hv-utils>=0.1.0
Requires-Dist: typing-extensions>=4.15.0
Maintainer: TwilightSparkle42
Maintainer-email: TwilightSparkle42 <jaden.corr42@gmail.com>
Requires-Python: >=3.12
Project-URL: Issue Tracker, https://github.com/HovorunBot/tlo/issues
Project-URL: Repository, https://github.com/HovorunBot/tlo
